cw_eval/__init__.py
cw_eval/baseeval.py
cw_eval/evalfunctions.py
cw_eval/challenge_eval/__init__.py
cw_eval/challenge_eval/off_nadir_dataset.py
cw_eval/challenge_eval/spacenet_eval.py
cw_eval/data/__init__.py
cw_eval/data/competition_test_results.csv
cw_eval/data/competition_test_results_full.csv
cw_eval/data/empty.geojson
cw_eval/data/gt.geojson
cw_eval/data/overlap_test.geojson
cw_eval/data/pred.geojson
cw_eval/data/sample_preds.csv
cw_eval/data/sample_preds_competition.csv
cw_eval/data/sample_truth.csv
cw_eval/data/sample_truth_competition.csv
cw_eval/data/test_results.csv
cw_eval/data/test_results_full.csv
cw_eval-1.0.0.dist-info/LICENSE
cw_eval-1.0.0.dist-info/METADATA
cw_eval-1.0.0.dist-info/WHEEL
cw_eval-1.0.0.dist-info/entry_points.txt
cw_eval-1.0.0.dist-info/top_level.txt
cw_eval-1.0.0.dist-info/RECORD
